sqlalchemy_mutable/__init__.py
sqlalchemy_mutable/dict.py
sqlalchemy_mutable/html.py
sqlalchemy_mutable/list.py
sqlalchemy_mutable/model_shell.py
sqlalchemy_mutable/mutable.py
sqlalchemy_mutable/set.py
sqlalchemy_mutable/tuple.py
sqlalchemy_mutable/types.py
sqlalchemy_mutable/utils.py
sqlalchemy_mutable-1.0.2.dist-info/LICENSE
sqlalchemy_mutable-1.0.2.dist-info/METADATA
sqlalchemy_mutable-1.0.2.dist-info/WHEEL
sqlalchemy_mutable-1.0.2.dist-info/top_level.txt
sqlalchemy_mutable-1.0.2.dist-info/RECORD
