Metadata-Version: 2.1
Name: sqlalchemy-mutable
Version: 1.0.2
Summary: SQLAlchemy Mutable provided utilities for creating flexible and powerful database columns for use with SQLAlchemy.
Home-page: https://dsbowen.gitlab.io/sqlalchemy-mutable
Author: Dillon Bowen
Author-email: dsbowen@wharton.upenn.edu
License: UNKNOWN
Platform: UNKNOWN
Classifier: Programming Language :: Python :: 3
Classifier: License :: OSI Approved :: MIT License
Classifier: Operating System :: OS Independent
Requires-Python: >=3.8
License-File: LICENSE
